odoo10_addon_stock_operation_package_mandatory-10.0.1.0.1-py3.8-nspkg.pth
odoo/addons/stock_operation_package_mandatory/README.rst
odoo/addons/stock_operation_package_mandatory/__init__.py
odoo/addons/stock_operation_package_mandatory/__manifest__.py
odoo/addons/stock_operation_package_mandatory/i18n/cs_CZ.po
odoo/addons/stock_operation_package_mandatory/i18n/stock_operation_package_mandatory.pot
odoo/addons/stock_operation_package_mandatory/models/__init__.py
odoo/addons/stock_operation_package_mandatory/models/stock_picking.py
odoo/addons/stock_operation_package_mandatory/models/stock_picking_type.py
odoo/addons/stock_operation_package_mandatory/static/description/icon.png
odoo/addons/stock_operation_package_mandatory/tests/__init__.py
odoo/addons/stock_operation_package_mandatory/tests/test_stock_operation_package_mandatory.py
odoo/addons/stock_operation_package_mandatory/views/stock_picking_type.xml
odoo10_addon_stock_operation_package_mandatory-10.0.1.0.1.dist-info/METADATA
odoo10_addon_stock_operation_package_mandatory-10.0.1.0.1.dist-info/WHEEL
odoo10_addon_stock_operation_package_mandatory-10.0.1.0.1.dist-info/namespace_packages.txt
odoo10_addon_stock_operation_package_mandatory-10.0.1.0.1.dist-info/top_level.txt
odoo10_addon_stock_operation_package_mandatory-10.0.1.0.1.dist-info/RECORD
